eversend/__init__.py
eversend/eversend.py
tests/__init__.py
tests/test_eversend.py
eversend_api-0.1.0.dist-info/LICENCE
eversend_api-0.1.0.dist-info/METADATA
eversend_api-0.1.0.dist-info/WHEEL
eversend_api-0.1.0.dist-info/top_level.txt
eversend_api-0.1.0.dist-info/RECORD
