Metadata-Version: 2.1
Name: eversend-api
Version: 0.1.0
Summary: Unofficial SDK for Eversend Business Platform
Home-page: UNKNOWN
Author: @0xdvvid
License: MIT
Platform: UNKNOWN
License-File: LICENCE
